stocktweepy/__init__.py
stocktweepy-0.0.1.dist-info/LICENSE
stocktweepy-0.0.1.dist-info/METADATA
stocktweepy-0.0.1.dist-info/WHEEL
stocktweepy-0.0.1.dist-info/top_level.txt
stocktweepy-0.0.1.dist-info/zip-safe
stocktweepy-0.0.1.dist-info/RECORD
