Metadata-Version: 2.1
Name: stocktweepy
Version: 0.0.1
Summary: StockTwits library for Python
Home-page: https://www.stocktweepy.org/
Author: JohnPatrickRoach
Author-email: contact@johnpatrickroach.com
License: MIT
Download-URL: https://pypi.org/project/stocktweepy/
Project-URL: Documentation, https://stocktweepy.readthedocs.io/
Project-URL: Issue Tracker, https://github.com/stocktweepy/stocktweepy/issues
Project-URL: Source Code, https://github.com/stocktweepy/stocktweepy
Keywords: twitter library
Platform: UNKNOWN
Classifier: Development Status :: 5 - Production/Stable
Classifier: Topic :: Software Development :: Libraries
Classifier: License :: OSI Approved :: MIT License
Classifier: Operating System :: OS Independent
Classifier: Programming Language :: Python
Classifier: Programming Language :: Python :: 2
Classifier: Programming Language :: Python :: 2.7
Classifier: Programming Language :: Python :: 3
Classifier: Programming Language :: Python :: 3.5
Classifier: Programming Language :: Python :: 3.6
Classifier: Programming Language :: Python :: 3.7
Classifier: Programming Language :: Python :: 3.8
Requires-Python: >=2.7, !=3.0.*, !=3.1.*, !=3.2.*, !=3.3.*, !=3.4.*
Requires-Dist: requests[socks] (>=2.11.1)
Requires-Dist: requests-oauthlib (>=0.7.0)
Requires-Dist: six (>=1.10.0)
Provides-Extra: dev
Requires-Dist: coveralls (>=1.8.2) ; extra == 'dev'
Requires-Dist: tox (>=2.4.0) ; extra == 'dev'
Provides-Extra: test
Requires-Dist: mock (>=1.0.1) ; extra == 'test'
Requires-Dist: nose (>=1.3.3) ; extra == 'test'
Requires-Dist: vcrpy (>=1.10.3) ; extra == 'test'
